<DIDL-Lite xmlns:dc="http://purl.org/dc/elements/1.1/" xmlns:upnp="urn:schemas-upnp-org:metadata-1-0/upnp/" xmlns:r="urn:schemas-rinconnetworks-com:metadata-1-0/" xmlns="urn:schemas-upnp-org:metadata-1-0/DIDL-Lite/">
  <container id="S://TLE-SERVER/share/mp3/Trentem%c3%b8ller%20-%20The%20Trentem%c3%b8ller%20Chronicles/-%3dTrentem%c3%b8ller%20-%20The%20Trentem%c3%b8ller%20Chronicles%20(CD%202).m3u" parentID="A:PLAYLISTS" restricted="true">
    <res protocolInfo="x-file-cifs:*:audio/mpegurl:*">x-file-cifs://TLE-SERVER/share/mp3/Trentem%c3%b8ller%20-%20The%20Trentem%c3%b8ller%20Chronicles/-%3dTrentem%c3%b8ller%20-%20The%20Trentem%c3%b8ller%20Chronicles%20(CD%202).m3u</res>
    <dc:title>-=Trentemøller - The Trentemøller Chronicles (CD 2).m3u</dc:title>
    <upnp:class>object.container.playlistContainer</upnp:class>
  </container>
  <container id="S://TLE-SERVER/share/mp3/Trentem%c3%b8ller%20-%20The%20Trentem%c3%b8ller%20Chronicles/-%3dTrentem%c3%b8ller%20-%20The%20Trentem%c3%b8ller%20Chronicles.m3u" parentID="A:PLAYLISTS" restricted="true">
    <res protocolInfo="x-file-cifs:*:audio/mpegurl:*">x-file-cifs://TLE-SERVER/share/mp3/Trentem%c3%b8ller%20-%20The%20Trentem%c3%b8ller%20Chronicles/-%3dTrentem%c3%b8ller%20-%20The%20Trentem%c3%b8ller%20Chronicles.m3u</res>
    <dc:title>-=Trentemøller - The Trentemøller Chronicles.m3u</dc:title>
    <upnp:class>object.container.playlistContainer</upnp:class>
  </container>
</DIDL-Lite>
